{
  "students": [
    {
      "id": 1,
      "firstName": "John",
      "lastName": "Doe",
      "active": true,
      "course_id": [
        1,
        2
      ]
    },
    {
      "active": false,
      "coursesIds": [],
      "firstName": "Janez",
      "lastName": "Smith",
      "id": 2
    }
  ],
  "courses": [
    {
      "id": 1,
      "name": "Intro to HTML",
      "description": "Start somewhere",
      "level": "100"
    },
    {
      "id": 2,
      "name": "Functional JavaScript",
      "description": "Because FUN",
      "level": "200"
    }
  ]
}